{
  "title": "Maxema - Pixel - Personalized and promotional pens. Promotional writing instruments and custom printed pens.",
  "description": "Pixel Square-cut lines that reflect a search for a perfect meld of clean-cut, essential shape and sober elegance. Particular attention has been dedicated to practicality with plenty of space for customisation which can be exploited very simply for screen or pad printing.",
  "headings": [
    {
      "level": 6,
      "text": "PRODUCTS"
    },
    {
      "level": 6,
      "text": "Services"
    },
    {
      "level": 6,
      "text": "COMPANY"
    },
    {
      "level": 1,
      "text": "Pixel"
    },
    {
      "level": 2,
      "text": "high resolution design"
    },
    {
      "level": 6,
      "text": "Technical information"
    },
    {
      "level": 3,
      "text": "P/Pixel"
    },
    {
      "level": 6,
      "text": "Details"
    },
    {
      "level": 4,
      "text": "A synthesis of contemporary style"
    },
    {
      "level": 4,
      "text": "Design with basic features: a feisty pen for dynamic brands"
    },
    {
      "level": 4,
      "text": "The ventilated push-button is compliant with EU laws for small components"
    },
    {
      "level": 6,
      "text": "Models and colors"
    },
    {
      "level": 4,
      "text": "PX40 - MATT CB AB"
    },
    {
      "level": 6,
      "text": "Show details"
    },
    {
      "level": 6,
      "text": "add to favorites"
    },
    {
      "level": 4,
      "text": "PX40 - MATT CB RE"
    },
    {
      "level": 6,
      "text": "Show details"
    },
    {
      "level": 6,
      "text": "add to favorites"
    },
    {
      "level": 4,
      "text": "PX40 - MATT RE"
    },
    {
      "level": 6,
      "text": "Show details"
    },
    {
      "level": 6,
      "text": "add to favorites"
    },
    {
      "level": 4,
      "text": "PX40 - B"
    },
    {
      "level": 6,
      "text": "Show details"
    },
    {
      "level": 6,
      "text": "add to favorites"
    },
    {
      "level": 4,
      "text": "PX40 - C"
    },
    {
      "level": 6,
      "text": "Show details"
    },
    {
      "level": 6,
      "text": "add to favorites"
    },
    {
      "level": 4,
      "text": "PX40 - MATT CB"
    },
    {
      "level": 6,
      "text": "Show details"
    },
    {
      "level": 6,
      "text": "add to favorites"
    },
    {
      "level": 4,
      "text": "PX40 - MATT CR"
    },
    {
      "level": 6,
      "text": "Show details"
    },
    {
      "level": 6,
      "text": "add to favorites"
    },
    {
      "level": 4,
      "text": "PX40 - 30"
    },
    {
      "level": 6,
      "text": "Show details"
    },
    {
      "level": 6,
      "text": "add to favorites"
    },
    {
      "level": 4,
      "text": "PX40 - FROST NEUTRAL"
    },
    {
      "level": 6,
      "text": "Show details"
    },
    {
      "level": 6,
      "text": "add to favorites"
    },
    {
      "level": 4,
      "text": "PX40 - FROST"
    },
    {
      "level": 6,
      "text": "Show details"
    },
    {
      "level": 6,
      "text": "add to favorites"
    },
    {
      "level": 4,
      "text": "PX40 - GOM C CR"
    },
    {
      "level": 6,
      "text": "Show details"
    },
    {
      "level": 6,
      "text": "add to favorites"
    },
    {
      "level": 4,
      "text": "PX40 - GOM 30 CR"
    },
    {
      "level": 6,
      "text": "Show details"
    },
    {
      "level": 6,
      "text": "add to favorites"
    },
    {
      "level": 6,
      "text": "Technical information"
    },
    {
      "level": 5,
      "text": "Features"
    },
    {
      "level": 5,
      "text": "Print areas"
    },
    {
      "level": 6,
      "text": "Customisations"
    }
  ],
  "images": [
    {
      "src": "http://www.maxema.com/assets/images/logo.gif",
      "alt": "Maxema promotional pens",
      "width": null,
      "height": null,
      "class": ""
    },
    {
      "src": "/assets/muvobit/landing/images/future/linkedin-logo.svg",
      "alt": "",
      "width": null,
      "height": null,
      "class": "img-social"
    },
    {
      "src": "/assets/muvobit/landing/images/future/instagram-logo.svg",
      "alt": "",
      "width": null,
      "height": null,
      "class": "img-social"
    },
    {
      "src": "/assets/muvobit/landing/images/future/youtube-logo.svg",
      "alt": "",
      "width": null,
      "height": null,
      "class": "img-social"
    },
    {
      "src": "http://www.maxema.com/media/production/pens/40x00_maxema-KINDMATTRP01.jpg",
      "alt": "",
      "width": "40",
      "height": null,
      "class": "hidden"
    },
    {
      "src": "http://www.maxema.com/media/production/pens/40x00_maxema-35921.jpg",
      "alt": "",
      "width": "40",
      "height": null,
      "class": "hidden"
    },
    {
      "src": "http://www.maxema.com/media/production/pens/40x00_maxema-207329.jpg",
      "alt": "",
      "width": "40",
      "height": null,
      "class": "hidden"
    },
    {
      "src": "http://www.maxema.com/media/production/pens/40x00_maxema-603236.jpg",
      "alt": "",
      "width": "40",
      "height": null,
      "class": "hidden"
    },
    {
      "src": "http://www.maxema.com/media/production/pens/40x00_maxema-797142.jpg",
      "alt": "",
      "width": "40",
      "height": null,
      "class": "hidden"
    },
    {
      "src": "http://www.maxema.com/media/production/pens/40x00_maxema-899440.jpg",
      "alt": "",
      "width": "40",
      "height": null,
      "class": "hidden"
    },
    {
      "src": "http://www.maxema.com/media/production/pens/40x00_maxema-147418.jpg",
      "alt": "",
      "width": "40",
      "height": null,
      "class": "hidden"
    },
    {
      "src": "http://www.maxema.com/media/production/pens/40x00_maxema-948235.jpg",
      "alt": "",
      "width": "40",
      "height": null,
      "class": "hidden"
    },
    {
      "src": "http://www.maxema.com/media/production/pens/40x00_maxema-151447.jpg",
      "alt": "",
      "width": "40",
      "height": null,
      "class": "hidden"
    },
    {
      "src": "http://www.maxema.com/media/production/pens/40x00_maxema-234846.jpg",
      "alt": "",
      "width": "40",
      "height": null,
      "class": "hidden"
    },
    {
      "src": "http://www.maxema.com/media/production/pens/40x00_maxema-297716.jpg",
      "alt": "",
      "width": "40",
      "height": null,
      "class": "hidden"
    },
    {
      "src": "http://www.maxema.com/media/production/pens/40x00_maxema-446924.jpg",
      "alt": "",
      "width": "40",
      "height": null,
      "class": "hidden"
    },
    {
      "src": "http://www.maxema.com/media/production/pens/40x00_maxema-572722.jpg",
      "alt": "",
      "width": "40",
      "height": null,
      "class": "hidden"
    },
    {
      "src": "http://www.maxema.com/media/production/pens/40x00_maxema-797263.jpg",
      "alt": "",
      "width": "40",
      "height": null,
      "class": "hidden"
    },
    {
      "src": "http://www.maxema.com/media/production/pens/40x00_maxema-312947.jpg",
      "alt": "",
      "width": "40",
      "height": null,
      "class": "hidden"
    },
    {
      "src": "http://www.maxema.com/media/production/pens/40x00_maxema-50384.jpg",
      "alt": "",
      "width": "40",
      "height": null,
      "class": "hidden"
    },
    {
      "src": "http://www.maxema.com/media/production/pens/40x00_maxema-440540.jpg",
      "alt": "",
      "width": "40",
      "height": null,
      "class": "hidden"
    },
    {
      "src": "http://www.maxema.com/media/production/pens/maxema-216443.jpg",
      "alt": "",
      "width": null,
      "height": null,
      "class": "img-responsive"
    },
    {
      "src": "http://www.maxema.com/media/production/pens/maxema-8990.jpg",
      "alt": "",
      "width": null,
      "height": null,
      "class": "img-responsive"
    },
    {
      "src": "http://www.maxema.com/media/production/pens/maxema-554390.jpg",
      "alt": "",
      "width": null,
      "height": null,
      "class": "img-responsive"
    },
    {
      "src": "http://www.maxema.com/media/production/pens/50x00_maxema-515517.jpg",
      "alt": "",
      "width": null,
      "height": "303",
      "class": ""
    },
    {
      "src": "/assets/images/loader_wh.gif",
      "alt": "",
      "width": null,
      "height": null,
      "class": ""
    },
    {
      "src": "http://www.maxema.com/media/production/pens/50x00_maxema-515517.jpg",
      "alt": "",
      "width": null,
      "height": null,
      "class": "pen_color_img"
    },
    {
      "src": "http://www.maxema.com/media/production/pens/50x00_maxema-686402.jpg",
      "alt": "",
      "width": null,
      "height": "303",
      "class": ""
    },
    {
      "src": "/assets/images/loader_wh.gif",
      "alt": "",
      "width": null,
      "height": null,
      "class": ""
    },
    {
      "src": "http://www.maxema.com/media/production/pens/50x00_maxema-156277.jpg",
      "alt": "",
      "width": null,
      "height": null,
      "class": "pen_color_img"
    },
    {
      "src": "http://www.maxema.com/media/production/pens/50x00_maxema-63256.jpg",
      "alt": "",
      "width": null,
      "height": null,
      "class": "pen_color_img"
    },
    {
      "src": "http://www.maxema.com/media/production/pens/50x00_maxema-666725.jpg",
      "alt": "",
      "width": null,
      "height": null,
      "class": "pen_color_img"
    },
    {
      "src": "http://www.maxema.com/media/production/pens/50x00_maxema-686402.jpg",
      "alt": "",
      "width": null,
      "height": null,
      "class": "pen_color_img"
    },
    {
      "src": "http://www.maxema.com/media/production/pens/50x00_maxema-941502.jpg",
      "alt": "",
      "width": null,
      "height": null,
      "class": "pen_color_img"
    },
    {
      "src": "http://www.maxema.com/media/production/pens/50x00_maxema-760099.jpg",
      "alt": "",
      "width": null,
      "height": null,
      "class": "pen_color_img"
    },
    {
      "src": "http://www.maxema.com/media/production/pens/50x00_maxema-111201.jpg",
      "alt": "",
      "width": null,
      "height": null,
      "class": "pen_color_img"
    },
    {
      "src": "http://www.maxema.com/media/production/pens/50x00_maxema-899440.jpg",
      "alt": "",
      "width": null,
      "height": "303",
      "class": ""
    },
    {
      "src": "/assets/images/loader_wh.gif",
      "alt": "",
      "width": null,
      "height": null,
      "class": ""
    },
    {
      "src": "http://www.maxema.com/media/production/pens/50x00_maxema-899440.jpg",
      "alt": "",
      "width": null,
      "height": null,
      "class": "pen_color_img"
    },
    {
      "src": "http://www.maxema.com/media/production/pens/50x00_maxema-988539.jpg",
      "alt": "",
      "width": null,
      "height": null,
      "class": "pen_color_img"
    },
    {
      "src": "http://www.maxema.com/media/production/pens/50x00_maxema-661509.jpg",
      "alt": "",
      "width": null,
      "height": null,
      "class": "pen_color_img"
    },
    {
      "src": "http://www.maxema.com/media/production/pens/50x00_maxema-859706.jpg",
      "alt": "",
      "width": null,
      "height": null,
      "class": "pen_color_img"
    },
    {
      "src": "http://www.maxema.com/media/production/pens/50x00_maxema-918869.jpg",
      "alt": "",
      "width": null,
      "height": null,
      "class": "pen_color_img"
    },
    {
      "src": "http://www.maxema.com/media/production/pens/50x00_maxema-877641.jpg",
      "alt": "",
      "width": null,
      "height": null,
      "class": "pen_color_img"
    },
    {
      "src": "http://www.maxema.com/media/production/pens/50x00_maxema-949803.jpg",
      "alt": "",
      "width": null,
      "height": null,
      "class": "pen_color_img"
    },
    {
      "src": "http://www.maxema.com/media/production/pens/50x00_maxema-542554.jpg",
      "alt": "",
      "width": null,
      "height": null,
      "class": "pen_color_img"
    },
    {
      "src": "http://www.maxema.com/media/production/pens/50x00_maxema-498225.jpg",
      "alt": "",
      "width": null,
      "height": "294",
      "class": ""
    },
    {
      "src": "/assets/images/loader_wh.gif",
      "alt": "",
      "width": null,
      "height": null,
      "class": ""
    },
    {
      "src": "http://www.maxema.com/media/production/pens/50x00_maxema-498225.jpg",
      "alt": "",
      "width": null,
      "height": null,
      "class": "pen_color_img"
    },
    {
      "src": "http://www.maxema.com/media/production/pens/50x00_maxema-809050.jpg",
      "alt": "",
      "width": null,
      "height": null,
      "class": "pen_color_img"
    },
    {
      "src": "http://www.maxema.com/media/production/pens/50x00_maxema-742406.jpg",
      "alt": "",
      "width": null,
      "height": null,
      "class": "pen_color_img"
    },
    {
      "src": "http://www.maxema.com/media/production/pens/50x00_maxema-213666.jpg",
      "alt": "",
      "width": null,
      "height": null,
      "class": "pen_color_img"
    },
    {
      "src": "http://www.maxema.com/media/production/pens/50x00_maxema-603885.jpg",
      "alt": "",
      "width": null,
      "height": null,
      "class": "pen_color_img"
    },
    {
      "src": "http://www.maxema.com/media/production/pens/50x00_maxema-839574.jpg",
      "alt": "",
      "width": null,
      "height": null,
      "class": "pen_color_img"
    },
    {
      "src": "http://www.maxema.com/media/production/pens/50x00_maxema-495749.jpg",
      "alt": "",
      "width": null,
      "height": null,
      "class": "pen_color_img"
    },
    {
      "src": "http://www.maxema.com/media/production/pens/50x00_maxema-292189.jpg",
      "alt": "",
      "width": null,
      "height": null,
      "class": "pen_color_img"
    },
    {
      "src": "http://www.maxema.com/media/production/pens/50x00_maxema-596843.jpg",
      "alt": "",
      "width": null,
      "height": null,
      "class": "pen_color_img"
    },
    {
      "src": "http://www.maxema.com/media/production/pens/50x00_maxema-858249.jpg",
      "alt": "",
      "width": null,
      "height": "294",
      "class": ""
    },
    {
      "src": "/assets/images/loader_wh.gif",
      "alt": "",
      "width": null,
      "height": null,
      "class": ""
    },
    {
      "src": "http://www.maxema.com/media/production/pens/50x00_maxema-30776.jpg",
      "alt": "",
      "width": null,
      "height": null,
      "class": "pen_color_img"
    },
    {
      "src": "http://www.maxema.com/media/production/pens/50x00_maxema-457969.jpg",
      "alt": "",
      "width": null,
      "height": null,
      "class": "pen_color_img"
    },
    {
      "src": "http://www.maxema.com/media/production/pens/50x00_maxema-188962.jpg",
      "alt": "",
      "width": null,
      "height": null,
      "class": "pen_color_img"
    },
    {
      "src": "http://www.maxema.com/media/production/pens/50x00_maxema-858249.jpg",
      "alt": "",
      "width": null,
      "height": null,
      "class": "pen_color_img"
    },
    {
      "src": "http://www.maxema.com/media/production/pens/50x00_maxema-577752.jpg",
      "alt": "",
      "width": null,
      "height": null,
      "class": "pen_color_img"
    },
    {
      "src": "http://www.maxema.com/media/production/pens/50x00_maxema-580986.jpg",
      "alt": "",
      "width": null,
      "height": null,
      "class": "pen_color_img"
    },
    {
      "src": "http://www.maxema.com/media/production/pens/50x00_maxema-914120.jpg",
      "alt": "",
      "width": null,
      "height": null,
      "class": "pen_color_img"
    },
    {
      "src": "http://www.maxema.com/media/production/pens/50x00_maxema-18667.jpg",
      "alt": "",
      "width": null,
      "height": null,
      "class": "pen_color_img"
    },
    {
      "src": "http://www.maxema.com/media/production/pens/50x00_maxema-948063.jpg",
      "alt": "",
      "width": null,
      "height": "303",
      "class": ""
    },
    {
      "src": "/assets/images/loader_wh.gif",
      "alt": "",
      "width": null,
      "height": null,
      "class": ""
    },
    {
      "src": "http://www.maxema.com/media/production/pens/50x00_maxema-948063.jpg",
      "alt": "",
      "width": null,
      "height": null,
      "class": "pen_color_img"
    },
    {
      "src": "http://www.maxema.com/media/production/pens/50x00_maxema-915192.jpg",
      "alt": "",
      "width": null,
      "height": null,
      "class": "pen_color_img"
    },
    {
      "src": "http://www.maxema.com/media/production/pens/50x00_maxema-448529.jpg",
      "alt": "",
      "width": null,
      "height": null,
      "class": "pen_color_img"
    },
    {
      "src": "http://www.maxema.com/media/production/pens/50x00_maxema-564816.jpg",
      "alt": "",
      "width": null,
      "height": null,
      "class": "pen_color_img"
    },
    {
      "src": "http://www.maxema.com/media/production/pens/50x00_maxema-50228.jpg",
      "alt": "",
      "width": null,
      "height": null,
      "class": "pen_color_img"
    },
    {
      "src": "http://www.maxema.com/media/production/pens/50x00_maxema-72452.jpg",
      "alt": "",
      "width": null,
      "height": null,
      "class": "pen_color_img"
    },
    {
      "src": "http://www.maxema.com/media/production/pens/50x00_maxema-990453.jpg",
      "alt": "",
      "width": null,
      "height": null,
      "class": "pen_color_img"
    },
    {
      "src": "http://www.maxema.com/media/production/pens/50x00_maxema-259878.jpg",
      "alt": "",
      "width": null,
      "height": null,
      "class": "pen_color_img"
    },
    {
      "src": "http://www.maxema.com/media/production/pens/50x00_maxema-944026.jpg",
      "alt": "",
      "width": null,
      "height": null,
      "class": "pen_color_img"
    },
    {
      "src": "http://www.maxema.com/media/production/pens/50x00_maxema-997816.jpg",
      "alt": "",
      "width": null,
      "height": null,
      "class": "pen_color_img"
    },
    {
      "src": "http://www.maxema.com/media/production/pens/50x00_maxema-156861.jpg",
      "alt": "",
      "width": null,
      "height": null,
      "class": "pen_color_img"
    },
    {
      "src": "http://www.maxema.com/media/production/pens/50x00_maxema-840855.jpg",
      "alt": "",
      "width": null,
      "height": null,
      "class": "pen_color_img"
    },
    {
      "src": "http://www.maxema.com/media/production/pens/50x00_maxema-62349.jpg",
      "alt": "",
      "width": null,
      "height": null,
      "class": "pen_color_img"
    },
    {
      "src": "http://www.maxema.com/media/production/pens/50x00_maxema-544134.jpg",
      "alt": "",
      "width": null,
      "height": null,
      "class": "pen_color_img"
    },
    {
      "src": "http://www.maxema.com/media/production/pens/50x00_maxema-270068.jpg",
      "alt": "",
      "width": null,
      "height": null,
      "class": "pen_color_img"
    },
    {
      "src": "http://www.maxema.com/media/production/pens/50x00_maxema-831898.jpg",
      "alt": "",
      "width": null,
      "height": null,
      "class": "pen_color_img"
    },
    {
      "src": "http://www.maxema.com/media/production/pens/50x00_maxema-674361.jpg",
      "alt": "",
      "width": null,
      "height": null,
      "class": "pen_color_img"
    },
    {
      "src": "http://www.maxema.com/media/production/pens/50x00_maxema-507821.jpg",
      "alt": "",
      "width": null,
      "height": null,
      "class": "pen_color_img"
    },
    {
      "src": "http://www.maxema.com/media/production/pens/50x00_maxema-177124.jpg",
      "alt": "",
      "width": null,
      "height": null,
      "class": "pen_color_img"
    },
    {
      "src": "http://www.maxema.com/media/production/pens/50x00_maxema-222677.jpg",
      "alt": "",
      "width": null,
      "height": null,
      "class": "pen_color_img"
    },
    {
      "src": "http://www.maxema.com/media/production/pens/50x00_maxema-955629.jpg",
      "alt": "",
      "width": null,
      "height": null,
      "class": "pen_color_img"
    },
    {
      "src": "http://www.maxema.com/media/production/pens/50x00_maxema-9448.jpg",
      "alt": "",
      "width": null,
      "height": null,
      "class": "pen_color_img"
    },
    {
      "src": "http://www.maxema.com/media/production/pens/50x00_maxema-460887.jpg",
      "alt": "",
      "width": null,
      "height": "303",
      "class": ""
    },
    {
      "src": "/assets/images/loader_wh.gif",
      "alt": "",
      "width": null,
      "height": null,
      "class": ""
    },
    {
      "src": "http://www.maxema.com/media/production/pens/50x00_maxema-460887.jpg",
      "alt": "",
      "width": null,
      "height": null,
      "class": "pen_color_img"
    },
    {
      "src": "http://www.maxema.com/media/production/pens/50x00_maxema-506159.jpg",
      "alt": "",
      "width": null,
      "height": null,
      "class": "pen_color_img"
    },
    {
      "src": "http://www.maxema.com/media/production/pens/50x00_maxema-247659.jpg",
      "alt": "",
      "width": null,
      "height": null,
      "class": "pen_color_img"
    },
    {
      "src": "http://www.maxema.com/media/production/pens/50x00_maxema-738935.jpg",
      "alt": "",
      "width": null,
      "height": null,
      "class": "pen_color_img"
    },
    {
      "src": "http://www.maxema.com/media/production/pens/50x00_maxema-638945.jpg",
      "alt": "",
      "width": null,
      "height": null,
      "class": "pen_color_img"
    },
    {
      "src": "http://www.maxema.com/media/production/pens/50x00_maxema-533042.jpg",
      "alt": "",
      "width": null,
      "height": null,
      "class": "pen_color_img"
    },
    {
      "src": "http://www.maxema.com/media/production/pens/50x00_maxema-698424.jpg",
      "alt": "",
      "width": null,
      "height": null,
      "class": "pen_color_img"
    },
    {
      "src": "http://www.maxema.com/media/production/pens/50x00_maxema-243981.jpg",
      "alt": "",
      "width": null,
      "height": null,
      "class": "pen_color_img"
    },
    {
      "src": "http://www.maxema.com/media/production/pens/50x00_maxema-550444.jpg",
      "alt": "",
      "width": null,
      "height": null,
      "class": "pen_color_img"
    },
    {
      "src": "http://www.maxema.com/media/production/pens/50x00_maxema-503085.jpg",
      "alt": "",
      "width": null,
      "height": null,
      "class": "pen_color_img"
    },
    {
      "src": "http://www.maxema.com/media/production/pens/50x00_maxema-839978.jpg",
      "alt": "",
      "width": null,
      "height": null,
      "class": "pen_color_img"
    },
    {
      "src": "http://www.maxema.com/media/production/pens/50x00_maxema-240684.jpg",
      "alt": "",
      "width": null,
      "height": null,
      "class": "pen_color_img"
    },
    {
      "src": "http://www.maxema.com/media/production/pens/50x00_maxema-318662.jpg",
      "alt": "",
      "width": null,
      "height": null,
      "class": "pen_color_img"
    },
    {
      "src": "http://www.maxema.com/media/production/pens/50x00_maxema-778927.jpg",
      "alt": "",
      "width": null,
      "height": null,
      "class": "pen_color_img"
    },
    {
      "src": "http://www.maxema.com/media/production/pens/50x00_maxema-424249.jpg",
      "alt": "",
      "width": null,
      "height": null,
      "class": "pen_color_img"
    },
    {
      "src": "http://www.maxema.com/media/production/pens/50x00_maxema-909133.jpg",
      "alt": "",
      "width": null,
      "height": null,
      "class": "pen_color_img"
    },
    {
      "src": "http://www.maxema.com/media/production/pens/50x00_maxema-467286.jpg",
      "alt": "",
      "width": null,
      "height": null,
      "class": "pen_color_img"
    },
    {
      "src": "http://www.maxema.com/media/production/pens/50x00_maxema-316376.jpg",
      "alt": "",
      "width": null,
      "height": null,
      "class": "pen_color_img"
    },
    {
      "src": "http://www.maxema.com/media/production/pens/50x00_maxema-37763.jpg",
      "alt": "",
      "width": null,
      "height": null,
      "class": "pen_color_img"
    },
    {
      "src": "http://www.maxema.com/media/production/pens/50x00_maxema-817733.jpg",
      "alt": "",
      "width": null,
      "height": null,
      "class": "pen_color_img"
    },
    {
      "src": "http://www.maxema.com/media/production/pens/50x00_maxema-703960.jpg",
      "alt": "",
      "width": null,
      "height": null,
      "class": "pen_color_img"
    },
    {
      "src": "http://www.maxema.com/media/production/pens/50x00_maxema-846436.jpg",
      "alt": "",
      "width": null,
      "height": null,
      "class": "pen_color_img"
    },
    {
      "src": "http://www.maxema.com/media/production/pens/50x00_maxema-53589.jpg",
      "alt": "",
      "width": null,
      "height": "294",
      "class": ""
    },
    {
      "src": "/assets/images/loader_wh.gif",
      "alt": "",
      "width": null,
      "height": null,
      "class": ""
    },
    {
      "src": "http://www.maxema.com/media/production/pens/50x00_maxema-53589.jpg",
      "alt": "",
      "width": null,
      "height": null,
      "class": "pen_color_img"
    },
    {
      "src": "http://www.maxema.com/media/production/pens/50x00_maxema-350820.jpg",
      "alt": "",
      "width": null,
      "height": null,
      "class": "pen_color_img"
    },
    {
      "src": "http://www.maxema.com/media/production/pens/50x00_maxema-463027.jpg",
      "alt": "",
      "width": null,
      "height": null,
      "class": "pen_color_img"
    },
    {
      "src": "http://www.maxema.com/media/production/pens/50x00_maxema-476792.jpg",
      "alt": "",
      "width": null,
      "height": null,
      "class": "pen_color_img"
    },
    {
      "src": "http://www.maxema.com/media/production/pens/50x00_maxema-311805.jpg",
      "alt": "",
      "width": null,
      "height": null,
      "class": "pen_color_img"
    },
    {
      "src": "http://www.maxema.com/media/production/pens/50x00_maxema-363396.jpg",
      "alt": "",
      "width": null,
      "height": null,
      "class": "pen_color_img"
    },
    {
      "src": "http://www.maxema.com/media/production/pens/50x00_maxema-640778.jpg",
      "alt": "",
      "width": null,
      "height": null,
      "class": "pen_color_img"
    },
    {
      "src": "http://www.maxema.com/media/production/pens/50x00_maxema-547650.jpg",
      "alt": "",
      "width": null,
      "height": null,
      "class": "pen_color_img"
    },
    {
      "src": "http://www.maxema.com/media/production/pens/50x00_maxema-632947.jpg",
      "alt": "",
      "width": null,
      "height": null,
      "class": "pen_color_img"
    },
    {
      "src": "http://www.maxema.com/media/production/pens/50x00_maxema-892985.jpg",
      "alt": "",
      "width": null,
      "height": null,
      "class": "pen_color_img"
    },
    {
      "src": "http://www.maxema.com/media/production/pens/50x00_maxema-186801.jpg",
      "alt": "",
      "width": null,
      "height": "294",
      "class": ""
    },
    {
      "src": "/assets/images/loader_wh.gif",
      "alt": "",
      "width": null,
      "height": null,
      "class": ""
    },
    {
      "src": "http://www.maxema.com/media/production/pens/50x00_maxema-835547.jpg",
      "alt": "",
      "width": null,
      "height": null,
      "class": "pen_color_img"
    },
    {
      "src": "http://www.maxema.com/media/production/pens/50x00_maxema-113526.jpg",
      "alt": "",
      "width": null,
      "height": null,
      "class": "pen_color_img"
    },
    {
      "src": "http://www.maxema.com/media/production/pens/50x00_maxema-171958.jpg",
      "alt": "",
      "width": null,
      "height": null,
      "class": "pen_color_img"
    },
    {
      "src": "http://www.maxema.com/media/production/pens/50x00_maxema-633491.jpg",
      "alt": "",
      "width": null,
      "height": null,
      "class": "pen_color_img"
    },
    {
      "src": "http://www.maxema.com/media/production/pens/50x00_maxema-478760.jpg",
      "alt": "",
      "width": null,
      "height": null,
      "class": "pen_color_img"
    },
    {
      "src": "http://www.maxema.com/media/production/pens/50x00_maxema-3604.jpg",
      "alt": "",
      "width": null,
      "height": null,
      "class": "pen_color_img"
    },
    {
      "src": "http://www.maxema.com/media/production/pens/50x00_maxema-555842.jpg",
      "alt": "",
      "width": null,
      "height": null,
      "class": "pen_color_img"
    },
    {
      "src": "http://www.maxema.com/media/production/pens/50x00_maxema-287040.jpg",
      "alt": "",
      "width": null,
      "height": null,
      "class": "pen_color_img"
    },
    {
      "src": "http://www.maxema.com/media/production/pens/50x00_maxema-186801.jpg",
      "alt": "",
      "width": null,
      "height": null,
      "class": "pen_color_img"
    },
    {
      "src": "http://www.maxema.com/media/production/pens/50x00_maxema-714007.jpg",
      "alt": "",
      "width": null,
      "height": "303",
      "class": ""
    },
    {
      "src": "/assets/images/loader_wh.gif",
      "alt": "",
      "width": null,
      "height": null,
      "class": ""
    },
    {
      "src": "http://www.maxema.com/media/production/pens/50x00_maxema-714007.jpg",
      "alt": "",
      "width": null,
      "height": null,
      "class": "pen_color_img"
    },
    {
      "src": "http://www.maxema.com/media/production/pens/50x00_maxema-273425.jpg",
      "alt": "",
      "width": null,
      "height": null,
      "class": "pen_color_img"
    },
    {
      "src": "http://www.maxema.com/media/production/pens/50x00_maxema-954344.jpg",
      "alt": "",
      "width": null,
      "height": null,
      "class": "pen_color_img"
    },
    {
      "src": "http://www.maxema.com/media/production/pens/50x00_maxema-157154.jpg",
      "alt": "",
      "width": null,
      "height": null,
      "class": "pen_color_img"
    },
    {
      "src": "http://www.maxema.com/media/production/pens/50x00_maxema-903009.jpg",
      "alt": "",
      "width": null,
      "height": null,
      "class": "pen_color_img"
    },
    {
      "src": "http://www.maxema.com/media/production/pens/50x00_maxema-755543.jpg",
      "alt": "",
      "width": null,
      "height": null,
      "class": "pen_color_img"
    },
    {
      "src": "http://www.maxema.com/media/production/pens/50x00_maxema-631818.jpg",
      "alt": "",
      "width": null,
      "height": null,
      "class": "pen_color_img"
    },
    {
      "src": "http://www.maxema.com/media/production/pens/50x00_maxema-912587.jpg",
      "alt": "",
      "width": null,
      "height": null,
      "class": "pen_color_img"
    },
    {
      "src": "http://www.maxema.com/media/production/pens/50x00_maxema-36476.jpg",
      "alt": "",
      "width": null,
      "height": null,
      "class": "pen_color_img"
    },
    {
      "src": "http://www.maxema.com/media/production/pens/50x00_maxema-771965.jpg",
      "alt": "",
      "width": null,
      "height": null,
      "class": "pen_color_img"
    },
    {
      "src": "http://www.maxema.com/media/production/pens/50x00_maxema-419429.jpg",
      "alt": "",
      "width": null,
      "height": null,
      "class": "pen_color_img"
    },
    {
      "src": "http://www.maxema.com/media/production/pens/50x00_maxema-468389.jpg",
      "alt": "",
      "width": null,
      "height": null,
      "class": "pen_color_img"
    },
    {
      "src": "http://www.maxema.com/media/production/pens/50x00_maxema-19872.jpg",
      "alt": "",
      "width": null,
      "height": null,
      "class": "pen_color_img"
    },
    {
      "src": "http://www.maxema.com/media/production/pens/50x00_maxema-919700.jpg",
      "alt": "",
      "width": null,
      "height": null,
      "class": "pen_color_img"
    },
    {
      "src": "http://www.maxema.com/media/production/pens/50x00_maxema-463322.jpg",
      "alt": "",
      "width": null,
      "height": null,
      "class": "pen_color_img"
    },
    {
      "src": "http://www.maxema.com/media/production/pens/50x00_maxema-400319.jpg",
      "alt": "",
      "width": null,
      "height": null,
      "class": "pen_color_img"
    },
    {
      "src": "http://www.maxema.com/media/production/pens/50x00_maxema-378278.jpg",
      "alt": "",
      "width": null,
      "height": null,
      "class": "pen_color_img"
    },
    {
      "src": "http://www.maxema.com/media/production/pens/50x00_maxema-452349.jpg",
      "alt": "",
      "width": null,
      "height": null,
      "class": "pen_color_img"
    },
    {
      "src": "http://www.maxema.com/media/production/pens/50x00_maxema-890260.jpg",
      "alt": "",
      "width": null,
      "height": null,
      "class": "pen_color_img"
    },
    {
      "src": "http://www.maxema.com/media/production/pens/50x00_maxema-798274.jpg",
      "alt": "",
      "width": null,
      "height": "294",
      "class": ""
    },
    {
      "src": "/assets/images/loader_wh.gif",
      "alt": "",
      "width": null,
      "height": null,
      "class": ""
    },
    {
      "src": "http://www.maxema.com/media/production/pens/50x00_maxema-297627.jpg",
      "alt": "",
      "width": null,
      "height": null,
      "class": "pen_color_img"
    },
    {
      "src": "http://www.maxema.com/media/production/pens/50x00_maxema-114914.jpg",
      "alt": "",
      "width": null,
      "height": null,
      "class": "pen_color_img"
    },
    {
      "src": "http://www.maxema.com/media/production/pens/50x00_maxema-243027.jpg",
      "alt": "",
      "width": null,
      "height": null,
      "class": "pen_color_img"
    },
    {
      "src": "http://www.maxema.com/media/production/pens/50x00_maxema-970777.jpg",
      "alt": "",
      "width": null,
      "height": null,
      "class": "pen_color_img"
    },
    {
      "src": "http://www.maxema.com/media/production/pens/50x00_maxema-874888.jpg",
      "alt": "",
      "width": null,
      "height": null,
      "class": "pen_color_img"
    },
    {
      "src": "http://www.maxema.com/media/production/pens/50x00_maxema-479612.jpg",
      "alt": "",
      "width": null,
      "height": null,
      "class": "pen_color_img"
    },
    {
      "src": "http://www.maxema.com/media/production/pens/50x00_maxema-25903.jpg",
      "alt": "",
      "width": null,
      "height": null,
      "class": "pen_color_img"
    },
    {
      "src": "http://www.maxema.com/media/production/pens/50x00_maxema-221561.jpg",
      "alt": "",
      "width": null,
      "height": null,
      "class": "pen_color_img"
    },
    {
      "src": "http://www.maxema.com/media/production/pens/50x00_maxema-798274.jpg",
      "alt": "",
      "width": null,
      "height": null,
      "class": "pen_color_img"
    },
    {
      "src": "http://www.maxema.com/media/production/pens/50x00_maxema-888214.jpg",
      "alt": "",
      "width": null,
      "height": "294",
      "class": ""
    },
    {
      "src": "/assets/images/loader_wh.gif",
      "alt": "",
      "width": null,
      "height": null,
      "class": ""
    },
    {
      "src": "http://www.maxema.com/media/production/pens/50x00_maxema-593067.jpg",
      "alt": "",
      "width": null,
      "height": null,
      "class": "pen_color_img"
    },
    {
      "src": "http://www.maxema.com/media/production/pens/50x00_maxema-697041.jpg",
      "alt": "",
      "width": null,
      "height": null,
      "class": "pen_color_img"
    },
    {
      "src": "http://www.maxema.com/media/production/pens/50x00_maxema-591575.jpg",
      "alt": "",
      "width": null,
      "height": null,
      "class": "pen_color_img"
    },
    {
      "src": "http://www.maxema.com/media/production/pens/50x00_maxema-588051.jpg",
      "alt": "",
      "width": null,
      "height": null,
      "class": "pen_color_img"
    },
    {
      "src": "http://www.maxema.com/media/production/pens/50x00_maxema-495496.jpg",
      "alt": "",
      "width": null,
      "height": null,
      "class": "pen_color_img"
    },
    {
      "src": "http://www.maxema.com/media/production/pens/50x00_maxema-468609.jpg",
      "alt": "",
      "width": null,
      "height": null,
      "class": "pen_color_img"
    },
    {
      "src": "http://www.maxema.com/media/production/pens/50x00_maxema-888214.jpg",
      "alt": "",
      "width": null,
      "height": null,
      "class": "pen_color_img"
    },
    {
      "src": "http://www.maxema.com/media/production/pens/50x00_maxema-248301.jpg",
      "alt": "",
      "width": null,
      "height": null,
      "class": "pen_color_img"
    },
    {
      "src": "http://www.maxema.com/media/production/techSpecs/210x00_maxema-techSpec_769650.jpg",
      "alt": "",
      "width": null,
      "height": "412",
      "class": ""
    },
    {
      "src": "http://www.maxema.com/media/production/pens/780x00_maxema-82581.jpg",
      "alt": "",
      "width": null,
      "height": "412",
      "class": ""
    },
    {
      "src": "/assets/images/icon_5.png",
      "alt": "maxema promotional pens",
      "width": null,
      "height": null,
      "class": ""
    },
    {
      "src": "/assets/muvobit/landing/images/future/linkedin-logo.svg",
      "alt": "",
      "width": null,
      "height": null,
      "class": "img-social img-social-footer"
    },
    {
      "src": "/assets/muvobit/landing/images/future/instagram-logo.svg",
      "alt": "",
      "width": null,
      "height": null,
      "class": "img-social img-social-footer"
    },
    {
      "src": "/assets/muvobit/landing/images/future/youtube-logo.svg",
      "alt": "",
      "width": null,
      "height": null,
      "class": "img-social img-social-footer"
    }
  ],
  "videos": [],
  "links": [
    {
      "href": "http://www.maxema.com/?l=en",
      "text": ""
    },
    {
      "href": "https://www.linkedin.com/company/maxema/",
      "text": ""
    },
    {
      "href": "https://www.instagram.com/maxema_official/",
      "text": ""
    },
    {
      "href": "https://www.youtube.com/user/MAXEMAchannel",
      "text": ""
    },
    {
      "href": "/product/it/61/?l=it",
      "text": "Italiano"
    },
    {
      "href": "/product/en/61/?l=en",
      "text": "English"
    },
    {
      "href": "http://www.maxema.com/favorites/en/",
      "text": "Reserved Area"
    },
    {
      "href": "http://www.maxema.com/contacts/en/",
      "text": "Contacts"
    },
    {
      "href": "http://www.maxema.com/about/en/",
      "text": "Company"
    },
    {
      "href": "http://www.maxema.com/products/en/",
      "text": "Pens"
    },
    {
      "href": "http://www.maxema.com/customisation/en/",
      "text": "Customisation"
    },
    {
      "href": "http://www.maxema.com/sample_cases/en/",
      "text": "Sample kits"
    },
    {
      "href": "http://www.maxema.com/finishes/en/",
      "text": "Finishes"
    },
    {
      "href": "http://www.maxema.com/recycled-plastic-pens/en/",
      "text": "Recycled pens"
    },
    {
      "href": "#",
      "text": "More"
    },
    {
      "href": "http://www.maxema.com/products/en/",
      "text": "PRODUCTS"
    },
    {
      "href": "http://www.maxema.com/product/en/0/",
      "text": "Kind /"
    },
    {
      "href": "http://www.maxema.com/product/en/261/",
      "text": "Kind /"
    },
    {
      "href": "http://www.maxema.com/product/en/235/",
      "text": "Icon Pure /"
    },
    {
      "href": "http://www.maxema.com/product/en/198/",
      "text": "Flow Pure /"
    },
    {
      "href": "http://www.maxema.com/product/en/161/",
      "text": "Dot /"
    },
    {
      "href": "http://www.maxema.com/product/en/157/",
      "text": "Zink /"
    },
    {
      "href": "http://www.maxema.com/product/en/61/",
      "text": "Pixel /"
    },
    {
      "href": "http://www.maxema.com/product/en/191/",
      "text": "Bay /"
    },
    {
      "href": "http://www.maxema.com/product/en/251/",
      "text": "Mood Metal /"
    },
    {
      "href": "http://www.maxema.com/product/en/252/",
      "text": "Kind /"
    },
    {
      "href": "http://www.maxema.com/product/en/217/",
      "text": "Mood /"
    },
    {
      "href": "http://www.maxema.com/product/en/171/",
      "text": "Flow /"
    },
    {
      "href": "http://www.maxema.com/product/en/120/",
      "text": "View /"
    },
    {
      "href": "http://www.maxema.com/product/en/124/",
      "text": "Tag Green /"
    },
    {
      "href": "http://www.maxema.com/product/en/44/",
      "text": "Next /"
    },
    {
      "href": "http://www.maxema.com/product/en/104/",
      "text": "Tag /"
    },
    {
      "href": "http://www.maxema.com/product/en/93/",
      "text": "Icon /"
    },
    {
      "href": "http://www.maxema.com/product/en/105/",
      "text": "Icon green /"
    },
    {
      "href": "http://www.maxema.com/product/en/73/",
      "text": "Ethic"
    },
    {
      "href": "http://www.maxema.com/search/en/9/",
      "text": "rose/purple"
    },
    {
      "href": "http://www.maxema.com/search/en/6/",
      "text": "azure / blue"
    },
    {
      "href": "http://www.maxema.com/search/en/7/",
      "text": "green"
    },
    {
      "href": "http://www.maxema.com/search/en/5/",
      "text": "yellow/orange"
    },
    {
      "href": "http://www.maxema.com/search/en/4/",
      "text": "red"
    },
    {
      "href": "http://www.maxema.com/search/en/10/",
      "text": "cream/brown"
    },
    {
      "href": "http://www.maxema.com/search/en/8/",
      "text": "grey"
    },
    {
      "href": "http://www.maxema.com/search/en/2/",
      "text": "black"
    },
    {
      "href": "http://www.maxema.com/search/en/1/",
      "text": "white"
    },
    {
      "href": "http://www.maxema.com/services/en/",
      "text": "Services"
    },
    {
      "href": "http://www.maxema.com/customisation/en/#sezione_stampa",
      "text": "customisation"
    },
    {
      "href": "http://www.maxema.com/customisation/en/#sezione_packaging",
      "text": "packaging"
    },
    {
      "href": "http://www.maxema.com/customisation/en/#sezione_pantone",
      "text": "pantone colors"
    },
    {
      "href": "http://www.maxema.com/sample_cases/en/",
      "text": "sample kits"
    },
    {
      "href": "http://www.maxema.com/about/en/",
      "text": "Maxema Company"
    },
    {
      "href": "http://www.maxema.com/contacts/en/",
      "text": "contacts"
    },
    {
      "href": "http://www.maxema.com/favorites/en/",
      "text": "FAVORITES"
    },
    {
      "href": "http://www.maxema.com/request-sample/en/",
      "text": "SAMPLE KITS"
    },
    {
      "href": "http://www.maxema.com/user-profile/en/",
      "text": "ACCOUNT"
    },
    {
      "href": "http://www.maxema.com/faq/en/",
      "text": "FAQ"
    },
    {
      "href": "http://www.maxema.com/media/en/",
      "text": "MEDIA"
    },
    {
      "href": "http://www.maxema.com/product/en/157/",
      "text": "previous model"
    },
    {
      "href": "http://www.maxema.com/product/en/191/",
      "text": "next model"
    },
    {
      "href": "http://www.maxema.com/",
      "text": "Home"
    },
    {
      "href": "http://www.maxema.com/products/en/",
      "text": "Pens Catalogue"
    },
    {
      "href": "#block1",
      "text": "1/4 Details"
    },
    {
      "href": "#block2",
      "text": "2/4 Variants"
    },
    {
      "href": "#block3",
      "text": "3/4 Technical information"
    },
    {
      "href": "#block4",
      "text": "4/4 Customisations"
    },
    {
      "href": "http://www.maxema.com/favorites/en/",
      "text": "log in"
    },
    {
      "href": "http://www.maxema.com/pen/en/258/5/",
      "text": ""
    },
    {
      "href": "http://www.maxema.com/pen/en/242/88/",
      "text": ""
    },
    {
      "href": "http://www.maxema.com/pen/en/242/89/",
      "text": ""
    },
    {
      "href": "http://www.maxema.com/pen/en/242/90/",
      "text": ""
    },
    {
      "href": "http://www.maxema.com/pen/en/242/91/",
      "text": ""
    },
    {
      "href": "http://www.maxema.com/pen/en/242/92/",
      "text": ""
    },
    {
      "href": "http://www.maxema.com/pen/en/242/93/",
      "text": ""
    },
    {
      "href": "http://www.maxema.com/pen/en/242/94/",
      "text": ""
    },
    {
      "href": "http://www.maxema.com/pen/en/243/87/",
      "text": ""
    },
    {
      "href": "http://www.maxema.com/pen/en/243/88/",
      "text": ""
    },
    {
      "href": "http://www.maxema.com/pen/en/243/89/",
      "text": ""
    },
    {
      "href": "http://www.maxema.com/pen/en/243/90/",
      "text": ""
    },
    {
      "href": "http://www.maxema.com/pen/en/243/91/",
      "text": ""
    },
    {
      "href": "http://www.maxema.com/pen/en/243/92/",
      "text": ""
    },
    {
      "href": "http://www.maxema.com/pen/en/243/93/",
      "text": ""
    },
    {
      "href": "http://www.maxema.com/pen/en/243/94/",
      "text": ""
    },
    {
      "href": "http://www.maxema.com/pen/en/72/5/",
      "text": ""
    },
    {
      "href": "http://www.maxema.com/pen/en/72/7/",
      "text": ""
    },
    {
      "href": "http://www.maxema.com/pen/en/72/8/",
      "text": ""
    },
    {
      "href": "http://www.maxema.com/pen/en/72/9/",
      "text": ""
    },
    {
      "href": "http://www.maxema.com/pen/en/72/10/",
      "text": ""
    },
    {
      "href": "http://www.maxema.com/pen/en/72/16/",
      "text": ""
    },
    {
      "href": "http://www.maxema.com/pen/en/72/20/",
      "text": ""
    },
    {
      "href": "http://www.maxema.com/pen/en/72/21/",
      "text": ""
    },
    {
      "href": "http://www.maxema.com/pen/en/72/22/",
      "text": ""
    },
    {
      "href": "http://www.maxema.com/pen/en/71/6/",
      "text": ""
    },
    {
      "href": "http://www.maxema.com/pen/en/71/7/",
      "text": ""
    },
    {
      "href": "http://www.maxema.com/pen/en/71/8/",
      "text": ""
    },
    {
      "href": "http://www.maxema.com/pen/en/71/9/",
      "text": ""
    },
    {
      "href": "http://www.maxema.com/pen/en/71/16/",
      "text": ""
    },
    {
      "href": "http://www.maxema.com/pen/en/71/20/",
      "text": ""
    },
    {
      "href": "http://www.maxema.com/pen/en/71/21/",
      "text": ""
    },
    {
      "href": "http://www.maxema.com/pen/en/71/22/",
      "text": ""
    },
    {
      "href": "http://www.maxema.com/pen/en/215/5/",
      "text": ""
    },
    {
      "href": "http://www.maxema.com/pen/en/215/6/",
      "text": ""
    },
    {
      "href": "http://www.maxema.com/pen/en/215/7/",
      "text": ""
    },
    {
      "href": "http://www.maxema.com/pen/en/215/8/",
      "text": ""
    },
    {
      "href": "http://www.maxema.com/pen/en/215/9/",
      "text": ""
    },
    {
      "href": "http://www.maxema.com/pen/en/215/10/",
      "text": ""
    },
    {
      "href": "http://www.maxema.com/pen/en/215/11/",
      "text": ""
    },
    {
      "href": "http://www.maxema.com/pen/en/215/12/",
      "text": ""
    },
    {
      "href": "http://www.maxema.com/pen/en/215/14/",
      "text": ""
    },
    {
      "href": "http://www.maxema.com/pen/en/215/15/",
      "text": ""
    },
    {
      "href": "http://www.maxema.com/pen/en/215/16/",
      "text": ""
    },
    {
      "href": "http://www.maxema.com/pen/en/215/17/",
      "text": ""
    },
    {
      "href": "http://www.maxema.com/pen/en/215/18/",
      "text": ""
    },
    {
      "href": "http://www.maxema.com/pen/en/215/20/",
      "text": ""
    },
    {
      "href": "http://www.maxema.com/pen/en/215/21/",
      "text": ""
    },
    {
      "href": "http://www.maxema.com/pen/en/215/22/",
      "text": ""
    },
    {
      "href": "http://www.maxema.com/pen/en/215/35/",
      "text": ""
    },
    {
      "href": "http://www.maxema.com/pen/en/215/37/",
      "text": ""
    },
    {
      "href": "http://www.maxema.com/pen/en/215/50/",
      "text": ""
    },
    {
      "href": "http://www.maxema.com/pen/en/215/59/",
      "text": ""
    },
    {
      "href": "http://www.maxema.com/pen/en/215/62/",
      "text": ""
    },
    {
      "href": "http://www.maxema.com/pen/en/215/74/",
      "text": ""
    },
    {
      "href": "http://www.maxema.com/pen/en/182/5/",
      "text": ""
    },
    {
      "href": "http://www.maxema.com/pen/en/182/6/",
      "text": ""
    },
    {
      "href": "http://www.maxema.com/pen/en/182/7/",
      "text": ""
    },
    {
      "href": "http://www.maxema.com/pen/en/182/8/",
      "text": ""
    },
    {
      "href": "http://www.maxema.com/pen/en/182/9/",
      "text": ""
    },
    {
      "href": "http://www.maxema.com/pen/en/182/10/",
      "text": ""
    },
    {
      "href": "http://www.maxema.com/pen/en/182/11/",
      "text": ""
    },
    {
      "href": "http://www.maxema.com/pen/en/182/12/",
      "text": ""
    },
    {
      "href": "http://www.maxema.com/pen/en/182/14/",
      "text": ""
    },
    {
      "href": "http://www.maxema.com/pen/en/182/15/",
      "text": ""
    },
    {
      "href": "http://www.maxema.com/pen/en/182/16/",
      "text": ""
    },
    {
      "href": "http://www.maxema.com/pen/en/182/17/",
      "text": ""
    },
    {
      "href": "http://www.maxema.com/pen/en/182/18/",
      "text": ""
    },
    {
      "href": "http://www.maxema.com/pen/en/182/20/",
      "text": ""
    },
    {
      "href": "http://www.maxema.com/pen/en/182/21/",
      "text": ""
    },
    {
      "href": "http://www.maxema.com/pen/en/182/22/",
      "text": ""
    },
    {
      "href": "http://www.maxema.com/pen/en/182/35/",
      "text": ""
    },
    {
      "href": "http://www.maxema.com/pen/en/182/37/",
      "text": ""
    },
    {
      "href": "http://www.maxema.com/pen/en/182/50/",
      "text": ""
    },
    {
      "href": "http://www.maxema.com/pen/en/182/59/",
      "text": ""
    },
    {
      "href": "http://www.maxema.com/pen/en/182/62/",
      "text": ""
    },
    {
      "href": "http://www.maxema.com/pen/en/182/74/",
      "text": ""
    },
    {
      "href": "http://www.maxema.com/pen/en/69/23/",
      "text": ""
    },
    {
      "href": "http://www.maxema.com/pen/en/69/24/",
      "text": ""
    },
    {
      "href": "http://www.maxema.com/pen/en/69/25/",
      "text": ""
    },
    {
      "href": "http://www.maxema.com/pen/en/69/26/",
      "text": ""
    },
    {
      "href": "http://www.maxema.com/pen/en/69/27/",
      "text": ""
    },
    {
      "href": "http://www.maxema.com/pen/en/69/28/",
      "text": ""
    },
    {
      "href": "http://www.maxema.com/pen/en/69/29/",
      "text": ""
    },
    {
      "href": "http://www.maxema.com/pen/en/69/30/",
      "text": ""
    },
    {
      "href": "http://www.maxema.com/pen/en/69/31/",
      "text": ""
    },
    {
      "href": "http://www.maxema.com/pen/en/69/32/",
      "text": ""
    },
    {
      "href": "http://www.maxema.com/pen/en/68/24/",
      "text": ""
    },
    {
      "href": "http://www.maxema.com/pen/en/68/25/",
      "text": ""
    },
    {
      "href": "http://www.maxema.com/pen/en/68/26/",
      "text": ""
    },
    {
      "href": "http://www.maxema.com/pen/en/68/27/",
      "text": ""
    },
    {
      "href": "http://www.maxema.com/pen/en/68/28/",
      "text": ""
    },
    {
      "href": "http://www.maxema.com/pen/en/68/29/",
      "text": ""
    },
    {
      "href": "http://www.maxema.com/pen/en/68/30/",
      "text": ""
    },
    {
      "href": "http://www.maxema.com/pen/en/68/31/",
      "text": ""
    },
    {
      "href": "http://www.maxema.com/pen/en/68/32/",
      "text": ""
    },
    {
      "href": "http://www.maxema.com/pen/en/67/23/",
      "text": ""
    },
    {
      "href": "http://www.maxema.com/pen/en/67/24/",
      "text": ""
    },
    {
      "href": "http://www.maxema.com/pen/en/67/25/",
      "text": ""
    },
    {
      "href": "http://www.maxema.com/pen/en/67/26/",
      "text": ""
    },
    {
      "href": "http://www.maxema.com/pen/en/67/27/",
      "text": ""
    },
    {
      "href": "http://www.maxema.com/pen/en/67/28/",
      "text": ""
    },
    {
      "href": "http://www.maxema.com/pen/en/67/29/",
      "text": ""
    },
    {
      "href": "http://www.maxema.com/pen/en/67/30/",
      "text": ""
    },
    {
      "href": "http://www.maxema.com/pen/en/67/31/",
      "text": ""
    },
    {
      "href": "http://www.maxema.com/pen/en/67/32/",
      "text": ""
    },
    {
      "href": "http://www.maxema.com/pen/en/67/60/",
      "text": ""
    },
    {
      "href": "http://www.maxema.com/pen/en/67/61/",
      "text": ""
    },
    {
      "href": "http://www.maxema.com/pen/en/67/63/",
      "text": ""
    },
    {
      "href": "http://www.maxema.com/pen/en/67/64/",
      "text": ""
    },
    {
      "href": "http://www.maxema.com/pen/en/67/65/",
      "text": ""
    },
    {
      "href": "http://www.maxema.com/pen/en/67/66/",
      "text": ""
    },
    {
      "href": "http://www.maxema.com/pen/en/67/67/",
      "text": ""
    },
    {
      "href": "http://www.maxema.com/pen/en/67/75/",
      "text": ""
    },
    {
      "href": "http://www.maxema.com/pen/en/67/76/",
      "text": ""
    },
    {
      "href": "http://www.maxema.com/pen/en/141/8/",
      "text": ""
    },
    {
      "href": "http://www.maxema.com/pen/en/141/9/",
      "text": ""
    },
    {
      "href": "http://www.maxema.com/pen/en/141/10/",
      "text": ""
    },
    {
      "href": "http://www.maxema.com/pen/en/141/11/",
      "text": ""
    },
    {
      "href": "http://www.maxema.com/pen/en/141/12/",
      "text": ""
    },
    {
      "href": "http://www.maxema.com/pen/en/141/15/",
      "text": ""
    },
    {
      "href": "http://www.maxema.com/pen/en/141/16/",
      "text": ""
    },
    {
      "href": "http://www.maxema.com/pen/en/141/21/",
      "text": ""
    },
    {
      "href": "http://www.maxema.com/pen/en/141/22/",
      "text": ""
    },
    {
      "href": "http://www.maxema.com/pen/en/142/25/",
      "text": ""
    },
    {
      "href": "http://www.maxema.com/pen/en/142/26/",
      "text": ""
    },
    {
      "href": "http://www.maxema.com/pen/en/142/28/",
      "text": ""
    },
    {
      "href": "http://www.maxema.com/pen/en/142/29/",
      "text": ""
    },
    {
      "href": "http://www.maxema.com/pen/en/142/30/",
      "text": ""
    },
    {
      "href": "http://www.maxema.com/pen/en/142/31/",
      "text": ""
    },
    {
      "href": "http://www.maxema.com/pen/en/142/60/",
      "text": ""
    },
    {
      "href": "http://www.maxema.com/pen/en/142/61/",
      "text": ""
    },
    {
      "href": "https://www.linkedin.com/company/maxema/",
      "text": ""
    },
    {
      "href": "https://www.instagram.com/maxema_official/",
      "text": ""
    },
    {
      "href": "https://www.youtube.com/user/MAXEMAchannel",
      "text": ""
    },
    {
      "href": "http://www.maxema.com/cookie_privacy_policy/en",
      "text": "privacy policy"
    }
  ],
  "forms": [],
  "mainTextChars": 5173,
  "mainText": "Italiano English Reserved Area Contacts Company Pens Customisation Sample kits Finishes Recycled pens More maxema ® via vittime delle foibe 15 10088 volpiano torino italy t +39 011 970 4500 f +39 011 970 4550 maxema@maxema.com P PRODUCTS Our pens Kind / Kind / Icon Pure / Flow Pure / Dot / Zink / Pixel / Bay / Mood Metal / Kind / Mood / Flow / View / Tag Green / Next / Tag / Icon / Icon green / Ethic Search by color rose/purple azure / blue green yellow/orange red cream/brown grey black white select a color S Services customisation packaging pantone colors sample kits C COMPANY Maxema Company contacts FAVORITES SAMPLE KITS ACCOUNT FAQ MEDIA DISCLAIMER previous model/ next model HomePens Catalogue Pixel Pixel high resolution design Technical information Download pdfof this model Square-cut lines that reflect a search for a perfect meld of clean-cut, essential shape and sober elegance. Particular attention has been dedicated to practicality with plenty of space for customisation which can be exploited very simply for screen or pad printing. Available in antibacterial and recycled plastic. 1/4 Details 2/4 Variants 3/4 Technical information 4/4 Customisations log in P/Pixel 1/4 Details Details of the pen A synthesis of contemporary style Design with basic features: a feisty pen for dynamic brands The ventilated push-button is compliant with EU laws for small components 2/4 Models and colors Available in 12 models and 132 color variants PX40 - MATT CB AB Show details add to favorites Antibacterial plastic, solid white colour barrel with matt finish, solid glossy white clip and push-button PX40 - MATT CB RE Show details add to favorites recycled plastic, solid colour barrel with matt finish, solid glossy white color clip and push-button PX40 - MATT RE Show details add to favorites recycled plastic, solid colour barrel with matt finish, solid glossy color clip and push-button PX40 - B Show details add to favorites ABS plastic, glossy finishes, solid colours, white barrel and push-button PX40 - C Show details add to favorites ABS plastic, glossy finishes, solid colours PX40 - MATT CB Show details add to favorites ABS plastic, solid colours, matt finish barrel, glossy finish white clip and push-button PX40 - MATT CR Show details add to favorites ABS plastic, solid colours, matt finish barrel, glossy finish clip, chromed push-button PX40 - 30 Show details add to favorites ABS plastic, glossy finishes, transparent colours PX40 - FROST NEUTRAL Show details add to favorites ABS plastic, transparent colours, neutral frosted barrel, glossy coloured clip, glossy neutral push-button PX40 - FROST Show details add to favorites ABS plastic, transparent colours, frosted barrel, glossy parts PX40 - GOM C CR Show details add to favorites ABS plastic, solid colours, rubber finish barrel, chromed push-button PX40 - GOM 30 CR Show details add to favorites ABS plastic, transparent colours, rubber finish barrel, chromed push-button 3/4 Technical information Print areas and tech specs Features ● retractable ● ventilated push-button ● made of non-toxic, highly resistant ABS plastic ● X-20 refill, blue and black ink ● the barrel is available in glossy, matt or rubberised finish ● rubberised barrel versions (GOM) are only printable on the clip Print areas 1 screen printing 50 x 25 mm * 2 pad printing 30 x 8 mm 3 pad printing 60 x 9 mm * * Not available for the following versions: - PX40 - GOM C CR - PX40 - GOM 30 CR 4/4 Customisations The brands mentioned in this catalogue are the exclusive property of the respective owners. They are used for purely illustrative purposes and cannot be the object of any buying and selling transactions, under any circumstances. via vittime delle foibe 15 10088 volpiano torino italy t +39 011 970 4500 f +39 011 970 4550 maxema@maxema.com MAXEMA SRL P.IVA 05321380015 privacy policy var acceptText='Accetto'; var policy_url='/cookie_privacy_policy/en'; var cookie_message='Il sito www.maxema.com utilizza cookie esclusivamente tecnici per permettere una corretta navigazione e la completa fruizione di tutti i contenuti da parte dell\\'utente. Non utilizziamo in alcun modo cookie di profilazione.'; var acceptText='I Understand'; var policy_url='/cookie_privacy_policy/en'; var cookie_message='This site uses cookies to improve their services and experience of readers. If you decide to continue browsing we consider that you accept their use.'; $(document).ready(function(){ $.cookieBar({ message: cookie_message, acceptButton: true, acceptText: acceptText, policyButton: true, policyText: 'Privacy Policy', policyURL: policy_url, autoEnable: true, acceptOnContinue: false, acceptOnScroll: false, acceptAnyClick: false, expireDays: 365, renewOnVisit: false, forceShow: false, bottom:true, fixed:true, domain: 'www.maxema.com', referrer: 'www.maxema.com' }); }); img.img-social {width: 16px;height: 16px;opacity: .6;transition: ease .5s;position: relative;top: 3px;} img.img-social:hover {opacity: 1;} .img-social-footer {filter: brightness(0.2);} .img-social-radius {width: 20px;height: 20px;display: inline-block;} .social_header {width: 84px !important;text-align: center;background: unset !important;}",
  "htmlBytes": 116328
}